rest_framework_util/__init__.py
rest_framework_util/apps.py
rest_framework_util/decorators.py
rest_framework_util/exceptions.py
rest_framework_util/fields.py
rest_framework_util/filters.py
rest_framework_util/log.py
rest_framework_util/mixins.py
rest_framework_util/pagination.py
rest_framework_util/response.py
rest_framework_util/routers.py
rest_framework_util/serializers.py
rest_framework_util/services.py
rest_framework_util/settings.py
rest_framework_util/urls.py
rest_framework_util/viewsets.py
rest_framework_util/core/__init__.py
rest_framework_util/core/cipher/__init__.py
rest_framework_util/core/cipher/backends/__init__.py
rest_framework_util/core/cipher/backends/aes.py
rest_framework_util/core/cipher/backends/base.py
rest_framework_util/core/storage/__init__.py
rest_framework_util/core/storage/backends/__init__.py
rest_framework_util/core/storage/backends/base.py
rest_framework_util/core/storage/backends/local.py
rest_framework_util/core/storage/backends/minio.py
rest_framework_util/core/upload/__init__.py
rest_framework_util/core/upload/backends.py
rest_framework_util/core/upload/configs.py
rest_framework_util/core/upload/settings.py
rest_framework_util/db/__init__.py
rest_framework_util/db/models/__init__.py
rest_framework_util/db/models/base.py
rest_framework_util/db/models/manager.py
rest_framework_util/db/models/query.py
rest_framework_util/middlewares/__init__.py
rest_framework_util/middlewares/agent.py
rest_framework_util/middlewares/csrf.py
rest_framework_util/middlewares/exception.py
rest_framework_util/middlewares/log.py
rest_framework_util/middlewares/response.py
rest_framework_util/middlewares/trace.py
djangorestframework_util-0.0.8.dist-info/LICENSE
djangorestframework_util-0.0.8.dist-info/METADATA
djangorestframework_util-0.0.8.dist-info/WHEEL
djangorestframework_util-0.0.8.dist-info/top_level.txt
djangorestframework_util-0.0.8.dist-info/RECORD
